dj_contentmodel/__init__.py
dj_contentmodel/admin.py
dj_contentmodel/models.py
dj_contentmodel/templates/dj_contentmodel/base.html
dj_contentmodel/templates/dj_contentmodel/sitemap.html
dj_contentmodel/templates/dj_contentmodel/taxonomy.html
dj_contentmodel-0.1.7.dist-info/DESCRIPTION.rst
dj_contentmodel-0.1.7.dist-info/METADATA
dj_contentmodel-0.1.7.dist-info/RECORD
dj_contentmodel-0.1.7.dist-info/WHEEL
dj_contentmodel-0.1.7.dist-info/metadata.json
dj_contentmodel-0.1.7.dist-info/top_level.txt
