Metadata-Version: 2.0
Name: dj-contentmodel
Version: 0.1.7
Summary: Pluggable app for taxonomies, content collections, and navigation.
Home-page: https://github.com/infosmith/dj-contentmodel
Author: David S.
Author-email: infosmith@protonmail.com
License: BSD
Keywords: dj-contentmodel
Platform: UNKNOWN
Classifier: Development Status :: 3 - Alpha
Classifier: Framework :: Django
Classifier: Framework :: Django :: 1.8
Classifier: Framework :: Django :: 1.9
Classifier: Intended Audience :: Developers
Classifier: License :: OSI Approved :: BSD License
Classifier: Natural Language :: English
Classifier: Programming Language :: Python :: 2
Classifier: Programming Language :: Python :: 2.7
Classifier: Programming Language :: Python :: 3
Classifier: Programming Language :: Python :: 3.3
Classifier: Programming Language :: Python :: 3.4
Classifier: Programming Language :: Python :: 3.5
Requires-Dist: django-model-utils (>=2.0)
